Metadata-Version: 1.0
Name: HeadFirstPython
Version: 0.0.1
Summary: Python REST API client for Guacamole 0.9.13 version
Home-page: https://github.com/ChenBin113
Author: right_now
Author-email: 1051136665@qq.com
License: UNKNOWN
Platform: UNKNOWN
